<?xml version="1.0" encoding="UTF-8"?>
<pricing>
  <evaluationTime>2013-08-30</evaluationTime>
  <itemCode>50507A3714S0</itemCode>
  <pricingParameter>
    <notional>418550000</notional>
    <underlyingInfo>
      <underlying>
        <krCode>KR7005380001</krCode>
        <underName>KR7005380001</underName>
        <currentValue>249000</currentValue>
        <drift>0.029</drift>
        <dividend>0.008172</dividend>
        <volatility>0.2646</volatility>
      </underlying>
      <underlying>
        <krCode>KR7005930003</krCode>
        <underName>KR7005930003</underName>
        <currentValue>1368000</currentValue>
        <drift>0.029</drift>
        <dividend>0.00625</dividend>
        <volatility>0.2551</volatility>
      </underlying>
      <corr>0.309548</corr>
    </underlyingInfo>
    <method>monte</method>
    <simulationNum>100000</simulationNum>
    <dicountFlatTS>0.029</dicountFlatTS>
    <instrumentInfo>
      <kiEvent>false</kiEvent>
    </instrumentInfo>
  </pricingParameter>
  <pricingResult>
    <price>420391341</price>
    <unitPrice unit="10000">10044</unitPrice>
    <greek>
      <underlying>
        <delta>
          <value>0.00486752</value>
        </delta>
        <gamma>
          <value>1.41156e-008</value>
        </gamma>
        <vega>
          <value>-21.2846</value>
        </vega>
      </underlying>
      <underlying>
        <delta>
          <value>0.000963879</value>
        </delta>
        <gamma>
          <value>5.66627e-010</value>
        </gamma>
        <vega>
          <value>-23.5131</value>
        </vega>
      </underlying>
      <theta>
        <value>100</value>
      </theta>
    </greek>
  </pricingResult>
  <pricingResult>
    <price>420391341</price>
    <unitPrice unit="10000">10044</unitPrice>
    <greek>
      <underlying>
        <delta>
          <value>0.00486752</value>
        </delta>
        <gamma>
          <value>1.41156e-008</value>
        </gamma>
        <vega>
          <value>-21.2846</value>
        </vega>
      </underlying>
      <underlying>
        <delta>
          <value>0.000963879</value>
        </delta>
        <gamma>
          <value>5.66627e-010</value>
        </gamma>
        <vega>
          <value>-23.5131</value>
        </vega>
      </underlying>
      <theta>
        <value>100</value>
      </theta>
    </greek>
  </pricingResult>
</pricing>